image_processing/__init__.py
image_processing/imagens/__init__.py
image_processing/imagens/combination.py
image_processing/imagens/transformation.py
image_processing/utils/__init__.py
image_processing/utils/io.py
image_processing/utils/plot.py
image_processing_louise-0.0.2.dist-info/METADATA
image_processing_louise-0.0.2.dist-info/WHEEL
image_processing_louise-0.0.2.dist-info/top_level.txt
image_processing_louise-0.0.2.dist-info/RECORD
